rindap/__init__.py
rindap/compat.py
rindap/base/__init__.py
rindap/base/deserialize.py
rindap/base/domain.py
rindap/base/exceptions.py
rindap/base/instance_context.py
rindap/base/instance_resource.py
rindap/base/list_resource.py
rindap/base/obsolete.py
rindap/base/page.py
rindap/base/serialize.py
rindap/base/values.py
rindap/base/version.py
rindap/http/__init__.py
rindap/http/http_client.py
rindap/http/request.py
rindap/http/response.py
rindap/rest/__init__.py
rindap/rest/v1/__init__.py
rindap/rest/v1/workspace/__init__.py
rindap/rest/v1/workspace/rate_limit_profile/__init__.py
rindap/rest/v1/workspace/task/__init__.py
rindap/rest/v1/workspace/task/reservation.py
rindap/rest/v1/workspace/task_queue/__init__.py
rindap/rest/v1/workspace/worker/__init__.py
rindap/rest/v1/workspace/worker/reservation.py
rindap/rest/v1/workspace/workflow/__init__.py
rindap-1.2.dist-info/METADATA
rindap-1.2.dist-info/WHEEL
rindap-1.2.dist-info/top_level.txt
rindap-1.2.dist-info/RECORD
