Metadata-Version: 2.1
Name: rindap
Version: 1.2
Summary: Rindap API
Home-page: https://rindap.com/
Author: Rindap
Author-email: dp@rindap.com
License: UNKNOWN
Keywords: Rindap,REST API for BPM,Business Process Management,Workflow Automation,BPM,Business Process Automation,BPMS,Workflow Management
Platform: UNKNOWN
Classifier: Development Status :: 5 - Production/Stable
Classifier: Intended Audience :: Developers
Classifier: License :: OSI Approved :: MIT License
Classifier: Operating System :: OS Independent
Classifier: Programming Language :: Python
Classifier: Programming Language :: Python :: 2.7
Classifier: Programming Language :: Python :: 3.4
Classifier: Programming Language :: Python :: 3.5
Classifier: Programming Language :: Python :: 3.6
Classifier: Programming Language :: Python :: 3.7
Classifier: Programming Language :: Python :: 3.8
Classifier: Programming Language :: Python :: Implementation :: CPython
Classifier: Topic :: Software Development :: Libraries :: Python Modules
Requires-Dist: six
Requires-Dist: pytz
Requires-Dist: requests[security] (>=2.0.0) ; python_version<"3.0"
Requires-Dist: requests (>=2.0.0) ; python_version>="3.0"
